{"FORLOOP": 39, "LOADK": 3, "TESTSET": 31, "RETURN": 38, "SUB": 15, "BOR": 22, "MOVE": 2, "NEWTABLE": 11, "SETLIST": 43, "SETTABLE": 10, "BNOT": 27, "TFORCALL": 41, "GETUPVAL": 7, "MUL": 16, "DIV": 19, "CONCAT": 13, "LE": 35, "LOADBOOL": 5, "SETTABUP": 8, "POW": 18, "JMP": 32, "FORPREP": 40, "LT": 34, "TFORLOOP": 42, "TEST": 30, "CLOSURE": 44, "SHR": 25, "LOADKX": 4, "BAND": 21, "ADD": 14, "SETUPVAL": 9, "EXTRAARG": 46, "SHL": 24, "UNM": 26, "GETTABUP": 0, "EQ": 33, "LEN": 29, "LOADNIL": 6, "VARARG": 45, "SELF": 12, "IDIV": 20, "CALL": 36, "BXOR": 23, "NOT": 28, "TAILCALL": 37, "GETTABLE": 1, "MOD": 17}